{
  "metadata": {
    "country": "Gibraltar",
    "country_code": "GI",
    "source": "SSB",
    "url": "https://data.ssb.no/api/v0/dataset/1132.json?lang=en"
  },
  "data": [
    {
      "year": 1996,
      "value": 11958.0
    },
    {
      "year": 1997,
      "value": 54812632.0
    },
    {
      "year": 1998,
      "value": 17301000.0
    },
    {
      "year": 1999,
      "value": 48521519.0
    },
    {
      "year": 2000,
      "value": 27631.0
    },
    {
      "year": 2001,
      "value": 39293.0
    },
    {
      "year": 2002,
      "value": 89538.0
    },
    {
      "year": 2003,
      "value": 25000.0
    },
    {
      "year": 2004,
      "value": 33456.0
    },
    {
      "year": 2005,
      "value": 269907.0
    },
    {
      "year": 2006,
      "value": 698633.0
    },
    {
      "year": 2007,
      "value": 270151.0
    },
    {
      "year": 2008,
      "value": 443658.0
    },
    {
      "year": 2009,
      "value": 4806132.0
    },
    {
      "year": 2010,
      "value": 299225.0
    },
    {
      "year": 2011,
      "value": 96858.0
    },
    {
      "year": 2012,
      "value": 43271.0
    },
    {
      "year": 2013,
      "value": 164935.0
    },
    {
      "year": 2014,
      "value": 155678.0
    },
    {
      "year": 2015,
      "value": 109815.0
    },
    {
      "year": 2016,
      "value": 48545063.0
    },
    {
      "year": 2017,
      "value": 295603.0
    },
    {
      "year": 2018,
      "value": 12773870.0
    },
    {
      "year": 2019,
      "value": 1146873.0
    },
    {
      "year": 2020,
      "value": 417783.0
    },
    {
      "year": 2021,
      "value": 395129.0
    },
    {
      "year": 2022,
      "value": 4967745.0
    },
    {
      "year": 2023,
      "value": 3837690.0
    },
    {
      "year": 2024,
      "value": 3304197.0
    }
  ]
}