{
  "metadata": {
    "country": "Slovakia",
    "country_code": "SK",
    "source": "SSB",
    "url": "https://data.ssb.no/api/v0/dataset/1132.json?lang=en"
  },
  "data": [
    {
      "year": 1996,
      "value": 79885895.0
    },
    {
      "year": 1997,
      "value": 87281315.0
    },
    {
      "year": 1998,
      "value": 130672732.0
    },
    {
      "year": 1999,
      "value": 185285457.0
    },
    {
      "year": 2000,
      "value": 228386757.0
    },
    {
      "year": 2001,
      "value": 224913806.0
    },
    {
      "year": 2002,
      "value": 281638752.0
    },
    {
      "year": 2003,
      "value": 340391130.0
    },
    {
      "year": 2004,
      "value": 525558378.0
    },
    {
      "year": 2005,
      "value": 700612657.0
    },
    {
      "year": 2006,
      "value": 838337717.0
    },
    {
      "year": 2007,
      "value": 1510329866.0
    },
    {
      "year": 2008,
      "value": 1790977173.0
    },
    {
      "year": 2009,
      "value": 1921413717.0
    },
    {
      "year": 2010,
      "value": 2372715227.0
    },
    {
      "year": 2011,
      "value": 2197992932.0
    },
    {
      "year": 2012,
      "value": 2404208056.0
    },
    {
      "year": 2013,
      "value": 2576456851.0
    },
    {
      "year": 2014,
      "value": 3004645365.0
    },
    {
      "year": 2015,
      "value": 2812271600.0
    },
    {
      "year": 2016,
      "value": 3182904673.0
    },
    {
      "year": 2017,
      "value": 3345310717.0
    },
    {
      "year": 2018,
      "value": 3712412376.0
    },
    {
      "year": 2019,
      "value": 3667142221.0
    },
    {
      "year": 2020,
      "value": 3650247896.0
    },
    {
      "year": 2021,
      "value": 3332000265.0
    },
    {
      "year": 2022,
      "value": 3548304282.0
    },
    {
      "year": 2023,
      "value": 3952495276.0
    },
    {
      "year": 2024,
      "value": 4138454415.0
    }
  ]
}