{
  "dataset": {
    "dimension": {
      "Sektor": {
        "label": "sector",
        "category": {
          "index": {
            "C_OFF": 0,
            "6100": 1,
            "6500": 2
          },
          "label": {
            "C_OFF": "General government",
            "6100": "Central government",
            "6500": "Local government"
          }
        },
        "link": {
          "describedby": [
            {
              "extension": {
                "Sektor": "urn:ssb:classification:klass:39"
              }
            }
          ]
        }
      },
      "Art": {
        "label": "type",
        "category": {
          "index": {
            "A": 0,
            "A1": 1,
            "A2": 2,
            "A3": 3,
            "A4": 4,
            "A5": 5,
            "A51": 6,
            "A511": 7,
            "A512": 8,
            "A52": 9,
            "A521": 10,
            "A522": 11,
            "A523": 12,
            "A53": 13,
            "A531": 14,
            "A532": 15,
            "A54": 16,
            "A55": 17,
            "A551": 18,
            "A5511": 19,
            "A5512": 20,
            "A552": 21,
            "A6": 22,
            "A7": 23,
            "A71": 24,
            "A711": 25,
            "A712": 26,
            "A73": 27,
            "A74": 28,
            "A75": 29,
            "B": 30,
            "B1": 31,
            "B2": 32,
            "B3": 33,
            "B4": 34,
            "B41": 35,
            "B411": 36,
            "B412": 37,
            "B43": 38,
            "B5": 39,
            "B6": 40,
            "B7": 41,
            "B8": 42,
            "B81": 43,
            "B811": 44,
            "B812": 45,
            "B82": 46,
            "B83": 47,
            "B84": 48,
            "B9": 49,
            "B91": 50,
            "B911": 51,
            "B912": 52,
            "B92": 53,
            "C": 54,
            "D": 55,
            "D1": 56,
            "D11": 57,
            "D111": 58,
            "D112": 59,
            "D12": 60,
            "D2": 61,
            "D21": 62,
            "D22": 63,
            "D23": 64,
            "D3": 65,
            "D31": 66,
            "D32": 67,
            "E": 68,
            "F": 69,
            "W1": 70,
            "W2": 71,
            "W3": 72
          },
          "label": {
            "A": "Total revenue",
            "A1": "Taxes on income, wealth etc",
            "A2": "Taxes on goods and services",
            "A3": "Capital taxes",
            "A4": "Social security contributions",
            "A5": "Property income",
            "A51": "Interest",
            "A511": "Interest (excl. repurchase agreements)",
            "A512": "Interest from repurchase agreements",
            "A52": "Dividends",
            "A521": "Dividends (excl. Equinor)",
            "A522": "Dividends from Equinor",
            "A523": "Reinvested earnings mutual funds",
            "A53": "Withdrawals from income of quasi-corporations",
            "A531": "Withdrawal from SDFI",
            "A532": "Withdrawal from other activities",
            "A54": "Transfer from the Central bank",
            "A55": "Rent",
            "A551": "Taxes on natural resources",
            "A5511": "Taxes on natural resources petroleum",
            "A5512": "Taxes on natural resources excluding extraction of petroleum",
            "A552": "Rent of land, natural resources, etc",
            "A6": "Administrative fees and sales of goods and services",
            "A7": "Current transfers",
            "A71": "Grants from other general government units",
            "A711": "Grants from central government",
            "A712": "Grants from local government",
            "A73": "Fines, penalties and forfeits",
            "A74": "Other domestic transfers",
            "A75": "Transfers from the rest of the world",
            "B": "Expense",
            "B1": "Compensation of employees",
            "B2": "Use of goods and services",
            "B3": "Consumption of fixed capital and R&D",
            "B4": "Property expense",
            "B41": "Interest",
            "B411": "Interest (excl. repurchase agreements)",
            "B412": "Interest from repurchase agreements",
            "B43": "Rent on land, etc.",
            "B5": "Social benefits in kind",
            "B6": "Social benefits in cash",
            "B7": "Subsidies",
            "B8": "Current transfers",
            "B81": "Grants to other general government units",
            "B811": "Grants to central government",
            "B812": "Grants to local government",
            "B82": "Transfers to non-profit institutions serving households",
            "B83": "Other domestic transfers",
            "B84": "Transfers to the rest of the world",
            "B9": "Capital transfers",
            "B91": "Domestic capital transfers",
            "B911": "Investment grants",
            "B912": "Other capital transfers",
            "B92": "Capital transfers to the rest of the world",
            "C": "Change in net worth from transactions (A-B)",
            "D": "Net acquisitions of non-financial assets",
            "D1": "Gross acquisitions of fixed assets and R&D",
            "D11": "Acquisitions of fixed assets and R&D",
            "D111": "Acquisitions of fixed assets",
            "D112": "Acquisitions of R&D",
            "D12": "Disposals of fixed assets (-)",
            "D2": "Consumption of fixed capital and R&D (-)",
            "D21": "Consumption of fixed capital (-)",
            "D22": "Consumption of R&D (-)",
            "D23": "Consumption of fixed capital classified as non-financial assets (-)",
            "D3": "Net acquisitions of non-financial non-produced assets",
            "D31": "Acquisitions of non-financial non-produced assets",
            "D32": "Disposals of non-financial non-produced assets (-)",
            "E": "Total expenditure (B+D)",
            "F": "Net lending/borrowing (A-E)",
            "W1": "Wages and salaries (own account capital formation)",
            "W2": "Goods and services (own account capital formation)",
            "W3": "Consumption of fixed capital (own account capital formation)"
          }
        },
        "link": {
          "describedby": [
            {
              "extension": {
                "Art": "urn:ssb:classification:klass:530"
              }
            }
          ]
        }
      },
      "Tid": {
        "label": "year",
        "category": {
          "index": {
            "2000": 0,
            "2001": 1,
            "2002": 2,
            "2003": 3,
            "2004": 4,
            "2005": 5,
            "2006": 6,
            "2007": 7,
            "2008": 8,
            "2009": 9,
            "2010": 10,
            "2011": 11,
            "2012": 12,
            "2013": 13,
            "2014": 14,
            "2015": 15,
            "2016": 16,
            "2017": 17,
            "2018": 18,
            "2019": 19,
            "2020": 20,
            "2021": 21,
            "2022": 22,
            "2023": 23,
            "2024": 24
          },
          "label": {
            "2000": "2000",
            "2001": "2001",
            "2002": "2002",
            "2003": "2003",
            "2004": "2004",
            "2005": "2005",
            "2006": "2006",
            "2007": "2007",
            "2008": "2008",
            "2009": "2009",
            "2010": "2010",
            "2011": "2011",
            "2012": "2012",
            "2013": "2013",
            "2014": "2014",
            "2015": "2015",
            "2016": "2016",
            "2017": "2017",
            "2018": "2018",
            "2019": "2019",
            "2020": "2020",
            "2021": "2021",
            "2022": "2022",
            "2023": "2023",
            "2024": "2024"
          }
        }
      },
      "ContentsCode": {
        "label": "contents",
        "category": {
          "index": {
            "Belop": 0
          },
          "label": {
            "Belop": "Revenue and expenditure"
          },
          "unit": {
            "Belop": {
              "base": "NOK million",
              "decimals": 0
            }
          }
        }
      },
      "id": [
        "Sektor",
        "Art",
        "Tid",
        "ContentsCode"
      ],
      "size": [
        3,
        73,
        25,
        1
      ],
      "role": {
        "time": [
          "Tid"
        ],
        "metric": [
          "ContentsCode"
        ]
      }
    },
    "label": "10721: General government. Revenue and expenditure (NOK million), by sector, type, year and contents",
    "source": "Statistics Norway",
    "updated": "2025-06-05T06:00:00Z",
    "value": [
      850735,
      883355,
      863041,
      890778,
      993897,
      1128391,
      1298468,
      1369302,
      1528426,
      1361092,
      1441942,
      1588689,
      1672909,
      1670718,
      1700956,
      1696272,
      1696392,
      1800468,
      1985277,
      2040386,
      1874458,
      2447425,
      3615516,
      3188374,
      3203407,
      299100,
      312599,
      305225,
      311940,
      369137,
      436237,
      495447,
      497697,
      569036,
      483114,
      536692,
      597567,
      622598,
      587421,
      548320,
      503056,
      489016,
      532160,
      617372,
      619007,
      514962,
      908934,
      1549449,
      1141720,
      1068771,
      196985,
      201564,
      203303,
      205546,
      220572,
      237581,
      262634,
      286168,
      284585,
      283994,
      305365,
      317007,
      330535,
      345628,
      359308,
      372032,
      389807,
      411414,
      429961,
      438262,
      444682,
      477463,
      504768,
      511755,
      530939,
      1273,
      1328,
      1243,
      1532,
      1660,
      1768,
      2063,
      2576,
      1973,
      2431,
      2377,
      1754,
      1887,
      2246,
      1880,
      295,
      206,
      91,
      73,
      44,
      64,
      48,
      32,
      46,
      30,
      134646,
      144485,
      153713,
      158050,
      166331,
      175961,
      191525,
      207753,
      227353,
      235976,
      246345,
      262289,
      280572,
      296278,
      316450,
      329053,
      334779,
      344657,
      362660,
      382860,
      386761,
      408692,
      436091,
      479006,
      497915,
      173267,
      172773,
      146809,
      154832,
      174857,
      211625,
      279891,
      302658,
      368222,
      273527,
      262277,
      316971,
      339236,
      336952,
      367058,
      377080,
      363844,
      388388,
      443837,
      458788,
      387147,
      505527,
      960211,
      879611,
      918272,
      50174,
      61722,
      63598,
      64140,
      65151,
      73006,
      102357,
      129624,
      135264,
      94023,
      86220,
      89965,
      81726,
      85604,
      98310,
      105996,
      101452,
      101213,
      100004,
      99656,
      92678,
      71097,
      101997,
      179375,
      254540,
      47755,
      58266,
      60799,
      60269,
      59255,
      61130,
      76640,
      96060,
      121075,
      93327,
      85870,
      88961,
      81507,
      85454,
      98151,
      106084,
      97481,
      97803,
      92878,
      93273,
      85288,
      66216,
      95702,
      167303,
      230598,
      2419,
      3456,
      2799,
      3871,
      5896,
      11876,
      25717,
      33564,
      14189,
      696,
      350,
      1004,
      219,
      150,
      159,
      -88,
      3971,
      3410,
      7126,
      6383,
      7389,
      4881,
      6295,
      12072,
      23943,
      11094,
      16396,
      20776,
      23235,
      26222,
      33764,
      45857,
      57764,
      74799,
      75373,
      70774,
      95662,
      102687,
      113898,
      140558,
      159872,
      163720,
      177251,
      208672,
      240931,
      210381,
      230605,
      306467,
      402382,
      403313,
      9392,
      10650,
      15731,
      18102,
      21000,
      25625,
      33264,
      43759,
      57859,
      59884,
      57956,
      82309,
      88236,
      99011,
      117450,
      144122,
      147637,
      160975,
      191555,
      220442,
      194978,
      219622,
      270636,
      323576,
      340232,
      1702,
      5746,
      5045,
      5133,
      5222,
      8139,
      12593,
      14006,
      16940,
      15489,
      12818,
      13352,
      13887,
      14421,
      22646,
      15382,
      15742,
      15937,
      16738,
      20057,
      15030,
      10494,
      35258,
      78309,
      62578,
      0,
      0,
      0,
      0,
      0,
      0,
      0,
      0,
      0,
      0,
      0,
      0,
      565,
      466,
      463,
      368,
      341,
      339,
      379,
      432,
      373,
      489,
      573,
      497,
      503,
      96283,
      79413,
      59724,
      65306,
      81240,
      102916,
      128269,
      111891,
      153992,
      99887,
      101740,
      127408,
      150764,
      133413,
      123511,
      96042,
      67906,
      87496,
      115862,
      98559,
      59998,
      183349,
      529762,
      279087,
      236340,
      95396,
      76456,
      58596,
      62538,
      76825,
      99562,
      124845,
      108817,
      152576,
      98285,
      100258,
      125820,
      148445,
      131604,
      121447,
      94145,
      67188,
      86620,
      114510,
      97376,
      59075,
      181937,
      528720,
      277003,
      234153,
      887,
      2957,
      1128,
      2768,
      4415,
      3354,
      3424,
      3074,
      1417,
      1602,
      1482,
      1588,
      2319,
      1809,
      2064,
      1897,
      718,
      876,
      1353,
      1183,
      923,
      1412,
      1042,
      2084,
      2187,
      10685,
      10685,
      0,
      0,
      0,
      0,
      0,
      0,
      0,
      0,
      0,
      0,
      0,
      0,
      0,
      10419,
      26589,
      17726,
      14333,
      14798,
      19706,
      15169,
      11108,
      8094,
      17604,
      5032,
      4557,
      2712,
      2152,
      2244,
      1937,
      3407,
      3379,
      4167,
      4244,
      3544,
      3936,
      4058,
      4037,
      4678,
      4750,
      4177,
      4702,
      4966,
      4843,
      4384,
      5308,
      10876,
      10673,
      6475,
      4827,
      4329,
      2470,
      1896,
      1967,
      1642,
      3095,
      2098,
      2955,
      2856,
      2256,
      2453,
      2705,
      2690,
      2518,
      2418,
      2546,
      2021,
      2913,
      2690,
      2697,
      2905,
      6914,
      5952,
      2641,
      3587,
      3467,
      1770,
      1229,
      1217,
      588,
      2350,
      764,
      1842,
      1470,
      1373,
      1517,
      1781,
      1700,
      1536,
      1551,
      1403,
      939,
      1780,
      1505,
      1418,
      940,
      1050,
      1319,
      1180,
      1240,
      862,
      700,
      667,
      750,
      1054,
      745,
      1334,
      1113,
      1386,
      883,
      937,
      923,
      990,
      982,
      867,
      1143,
      1082,
      1133,
      1185,
      1279,
      1965,
      5864,
      4633,
      1461,
      205,
      228,
      242,
      256,
      277,
      295,
      312,
      1281,
      1212,
      1388,
      1288,
      1483,
      1354,
      1348,
      2161,
      2332,
      1631,
      2681,
      2053,
      2154,
      1687,
      2403,
      3962,
      4721,
      3834,
      40493,
      46438,
      47555,
      49618,
      54221,
      57085,
      58607,
      66494,
      71236,
      74959,
      81184,
      85515,
      90609,
      94471,
      99035,
      105471,
      107713,
      113120,
      119169,
      126968,
      123683,
      128629,
      145062,
      154590,
      164552,
      4970,
      4168,
      5193,
      9259,
      7119,
      8135,
      8300,
      5956,
      6021,
      7092,
      7703,
      7585,
      7470,
      7723,
      8905,
      9285,
      11027,
      10638,
      12203,
      14457,
      17158,
      18132,
      19903,
      21647,
      22929,
      0,
      0,
      0,
      0,
      0,
      0,
      0,
      0,
      0,
      0,
      0,
      0,
      0,
      0,
      0,
      0,
      0,
      0,
      0,
      0,
      0,
      0,
      0,
      0,
      0,
      0,
      0,
      0,
      0,
      0,
      0,
      0,
      0,
      0,
      0,
      0,
      0,
      0,
      0,
      0,
      0,
      0,
      0,
      0,
      0,
      0,
      0,
      0,
      0,
      0,
      0,
      0,
      0,
      0,
      0,
      0,
      0,
      0,
      0,
      0,
      0,
      0,
      0,
      0,
      0,
      0,
      0,
      0,
      0,
      0,
      0,
      0,
      0,
      0,
      0,
      794,
      865,
      833,
      1144,
      1364,
      1412,
      1686,
      1823,
      1860,
      1769,
      2207,
      2063,
      2034,
      2017,
      2500,
      2255,
      2941,
      3357,
      3290,
      3912,
      3755,
      5748,
      5493,
      5056,
      4416,
      4177,
      3302,
      4306,
      8116,
      5754,
      6431,
      6499,
      4127,
      4136,
      5186,
      5443,
      5515,
      5398,
      5660,
      6138,
      6618,
      7691,
      6913,
      8122,
      8969,
      8827,
      11256,
      13039,
      14943,
      16603,
      0,
      0,
      54,
      0,
      2,
      292,
      115,
      5,
      25,
      138,
      52,
      7,
      39,
      47,
      267,
      412,
      395,
      369,
      790,
      1576,
      1769,
      1128,
      1371,
      1648,
      1909,
      613881,
      667642,
      708346,
      755670,
      781910,
      817568,
      878381,
      938330,
      1007426,
      1071917,
      1127727,
      1184970,
      1239687,
      1304317,
      1382773,
      1463371,
      1516958,
      1575575,
      1637790,
      1721173,
      1893657,
      1932051,
      2080315,
      2265893,
      2438063,
      177046,
      194068,
      206108,
      219302,
      229084,
      239771,
      254501,
      274546,
      299590,
      320476,
      338534,
      359551,
      381380,
      404368,
      425766,
      443753,
      459919,
      480538,
      503228,
      527151,
      538376,
      566166,
      598767,
      639356,
      682931,
      78812,
      92102,
      100634,
      102223,
      106183,
      111109,
      119241,
      128449,
      140468,
      154044,
      161458,
      166927,
      172597,
      183576,
      195499,
      208979,
      216707,
      229965,
      239935,
      254528,
      268306,
      291643,
      320766,
      346987,
      361841,
      40629,
      41407,
      42521,
      43503,
      46705,
      48811,
      52917,
      58169,
      63689,
      69005,
      73948,
      79751,
      86992,
      88242,
      94583,
      102184,
      107079,
      112143,
      119317,
      127128,
      136643,
      146488,
      161687,
      176760,
      188146,
      26201,
      33035,
      32061,
      35020,
      31706,
      35818,
      55582,
      63400,
      54947,
      37248,
      33187,
      32933,
      28119,
      27437,
      27273,
      26865,
      24308,
      22644,
      24323,
      26068,
      23937,
      18815,
      30600,
      56403,
      80896,
      26001,
      32807,
      31801,
      34747,
      31425,
      35523,
      55272,
      63068,
      54586,
      36854,
      32760,
      32472,
      27638,
      26934,
      26629,
      26144,
      23516,
      21821,
      23490,
      25215,
      23055,
      17915,
      29650,
      55334,
      79751,
      23085,
      28742,
      28428,
      29371,
      25015,
      23939,
      33787,
      30801,
      34587,
      34337,
      32395,
      31864,
      27512,
      26899,
      26593,
      26194,
      23539,
      21476,
      23490,
      25215,
      23055,
      17915,
      29650,
      55334,
      79751,
      2916,
      4065,
      3373,
      5376,
      6410,
      11584,
      21485,
      32267,
      19999,
      2517,
      365,
      608,
      126,
      35,
      36,
      -50,
      -23,
      345,
      0,
      0,
      0,
      0,
      0,
      0,
      0,
      200,
      228,
      261,
      273,
      281,
      295,
      310,
      332,
      361,
      394,
      427,
      461,
      480,
      503,
      644,
      721,
      793,
      823,
      833,
      854,
      882,
      900,
      950,
      1069,
      1145,
      23328,
      27391,
      30127,
      33185,
      36895,
      39511,
      42329,
      42960,
      46846,
      50107,
      54407,
      56158,
      58747,
      61191,
      65665,
      69068,
      72452,
      74010,
      76031,
      78235,
      78347,
      86211,
      91611,
      100029,
      106809,
      197171,
      211440,
      227349,
      248762,
      256443,
      260761,
      269012,
      280665,
      300969,
      329324,
      348259,
      370012,
      389858,
      407523,
      431945,
      460634,
      478468,
      493374,
      505260,
      524244,
      579330,
      594546,
      615363,
      673385,
      730336,
      31615,
      34178,
      32861,
      35134,
      35042,
      36094,
      36482,
      36167,
      39642,
      43236,
      45490,
      45435,
      47126,
      49391,
      51560,
      55079,
      57838,
      59509,
      62192,
      65399,
      91388,
      87870,
      117813,
      102025,
      104279,
      28093,
      29667,
      32740,
      34353,
      36551,
      41909,
      44561,
      50444,
      55247,
      63110,
      66531,
      67269,
      68629,
      76333,
      82673,
      90221,
      93505,
      96945,
      99762,
      109070,
      123200,
      128494,
      127768,
      154152,
      158536,
      0,
      0,
      0,
      0,
      0,
      0,
      0,
      0,
      0,
      0,
      0,
      0,
      0,
      0,
      0,
      0,
      0,
      0,
      0,
      0,
      0,
      0,
      0,
      0,
      0,
      0,
      0,
      0,
      0,
      0,
      0,
      0,
      0,
      0,
      0,
      0,
      0,
      0,
      0,
      0,
      0,
      0,
      0,
      0,
      0,
      0,
      0,
      0,
      0,
      0,
      0,
      0,
      0,
      0,
      0,
      0,
      0,
      0,
      0,
      0,
      0,
      0,
      0,
      0,
      0,
      0,
      0,
      0,
      0,
      0,
      0,
      0,
      0,
      0,
      0,
      14709,
      14414,
      16175,
      16978,
      18534,
      21285,
      22417,
      23930,
      25732,
      29813,
      30306,
      31737,
      33378,
      36212,
      44072,
      48265,
      50771,
      55938,
      58997,
      63216,
      70422,
      73450,
      74578,
      81089,
      84549,
      3826,
      4222,
      4002,
      4017,
      4454,
      4428,
      4450,
      4771,
      5450,
      5619,
      5955,
      6320,
      6655,
      6977,
      6159,
      6209,
      6589,
      6561,
      6824,
      7048,
      9424,
      9983,
      2590,
      3395,
      2801,
      9559,
      11030,
      12564,
      13358,
      13562,
      16196,
      17694,
      21742,
      24064,
      27678,
      30271,
      29212,
      28596,
      33144,
      32442,
      35747,
      36146,
      34446,
      33941,
      38806,
      43355,
      45061,
      50599,
      69668,
      71186,
      10986,
      4355,
      3943,
      4187,
      3300,
      3785,
      3757,
      3531,
      6029,
      5366,
      5913,
      6935,
      6242,
      6257,
      7809,
      6589,
      6682,
      6446,
      7742,
      9350,
      54130,
      11817,
      15941,
      16795,
      24291,
      10224,
      3326,
      3196,
      3460,
      2501,
      1906,
      2838,
      2560,
      4891,
      4247,
      4645,
      5436,
      4962,
      4880,
      6687,
      5718,
      5859,
      5683,
      6906,
      8335,
      53063,
      10626,
      11443,
      12371,
      12152,
      0,
      0,
      0,
      0,
      0,
      0,
      0,
      622,
      796,
      1424,
      2464,
      2655,
      2764,
      3010,
      2739,
      2848,
      3594,
      3176,
      3563,
      4138,
      43459,
      7500,
      8644,
      9141,
      9464,
      0,
      0,
      0,
      0,
      0,
      0,
      0,
      1939,
      4095,
      2823,
      2182,
      2781,
      2198,
      1870,
      3948,
      2870,
      2265,
      2507,
      3343,
      4197,
      9604,
      3125,
      2799,
      3230,
      2688,
      762,
      1029,
      747,
      727,
      799,
      1878,
      919,
      970,
      1138,
      1120,
      1268,
      1500,
      1280,
      1377,
      1122,
      870,
      823,
      763,
      836,
      1016,
      1067,
      1191,
      4497,
      4424,
      12138,
      236854,
      215714,
      154695,
      135109,
      211987,
      310824,
      420087,
      430972,
      520999,
      289175,
      314215,
      403719,
      433221,
      366401,
      318183,
      232901,
      179434,
      224893,
      347488,
      319212,
      -19200,
      515374,
      1535200,
      922481,
      765343,
      9783,
      9328,
      13496,
      18104,
      18253,
      16843,
      22243,
      28858,
      35095,
      40455,
      30971,
      30761,
      25149,
      38572,
      47155,
      45476,
      53665,
      60156,
      68031,
      84595,
      69406,
      70620,
      71122,
      81262,
      86552,
      51436,
      52870,
      56997,
      63672,
      68484,
      69410,
      78593,
      89976,
      100896,
      110921,
      107452,
      113094,
      115077,
      131802,
      144660,
      151990,
      165169,
      173842,
      193933,
      214169,
      217404,
      220455,
      240023,
      262561,
      283505,
      51807,
      53253,
      57774,
      64077,
      69033,
      70096,
      79177,
      91053,
      102276,
      112297,
      108310,
      113587,
      115667,
      132395,
      145442,
      155083,
      165945,
      178906,
      197969,
      218895,
      221475,
      225978,
      246370,
      269528,
      291006,
      44777,
      45772,
      49768,
      55302,
      59372,
      59552,
      67174,
      77611,
      87277,
      95912,
      91069,
      95577,
      96884,
      111551,
      123036,
      130969,
      140354,
      151547,
      168825,
      187718,
      190650,
      193115,
      211762,
      232599,
      252362,
      7030,
      7482,
      8007,
      8775,
      9662,
      10544,
      12003,
      13442,
      14999,
      16385,
      17242,
      18010,
      18782,
      20844,
      22406,
      24114,
      25590,
      27359,
      29144,
      31177,
      30825,
      32863,
      34608,
      36929,
      38644,
      -371,
      -384,
      -777,
      -405,
      -549,
      -686,
      -585,
      -1077,
      -1380,
      -1376,
      -859,
      -493,
      -590,
      -594,
      -782,
      -3093,
      -775,
      -5063,
      -4035,
      -4726,
      -4071,
      -5522,
      -6347,
      -6966,
      -7501,
      -40946,
      -41747,
      -42892,
      -43933,
      -47155,
      -49271,
      -53390,
      -58689,
      -64266,
      -69652,
      -74624,
      -80439,
      -87656,
      -90091,
      -96549,
      -104284,
      -109265,
      -114530,
      -121855,
      -129848,
      -139350,
      -149366,
      -164728,
      -180004,
      -191529,
      -33392,
      -34882,
      -35468,
      -36259,
      -38236,
      -40532,
      -43486,
      -47511,
      -52065,
      -56425,
      -60092,
      -64359,
      -70411,
      -71966,
      -77431,
      -84029,
      -87740,
      -91881,
      -97565,
      -103632,
      -112033,
      -120454,
      -133455,
      -146262,
      -155940,
      -7237,
      -6525,
      -7053,
      -7244,
      -8469,
      -8279,
      -9431,
      -10658,
      -11624,
      -12580,
      -13856,
      -15392,
      -16581,
      -16276,
      -17152,
      -18155,
      -19340,
      -20262,
      -21752,
      -23496,
      -24610,
      -26034,
      -28232,
      -30498,
      -32205,
      -317,
      -340,
      -371,
      -430,
      -450,
      -460,
      -473,
      -520,
      -577,
      -647,
      -676,
      -688,
      -664,
      -1849,
      -1966,
      -2100,
      -2186,
      -2387,
      -2538,
      -2720,
      -2707,
      -2878,
      -3041,
      -3244,
      -3383,
      -707,
      -1795,
      -609,
      -1635,
      -3076,
      -3295,
      -2960,
      -2429,
      -1535,
      -815,
      -1857,
      -1894,
      -2272,
      -3139,
      -956,
      -2230,
      -2239,
      843,
      -4048,
      274,
      -8648,
      -470,
      -4173,
      -1295,
      -5424,
      734,
      1250,
      2032,
      1126,
      441,
      811,
      1049,
      1626,
      1532,
      1982,
      1965,
      2033,
      2129,
      2923,
      2388,
      3010,
      1700,
      2147,
      1207,
      1390,
      1181,
      2195,
      2004,
      2821,
      1839,
      -1441,
      -3045,
      -2641,
      -2761,
      -3517,
      -4106,
      -4009,
      -4055,
      -3067,
      -2796,
      -3822,
      -3928,
      -4402,
      -6062,
      -3345,
      -5240,
      -3939,
      -1304,
      -5255,
      -1116,
      -9829,
      -2664,
      -6177,
      -4116,
      -7263,
      623664,
      676970,
      721842,
      773773,
      800163,
      834411,
      900624,
      967188,
      1042522,
      1112371,
      1158698,
      1215731,
      1264836,
      1342889,
      1429928,
      1508848,
      1570624,
      1635730,
      1705820,
      1805768,
      1963064,
      2002671,
      2151437,
      2347156,
      2524615,
      227071,
      206386,
      141199,
      117005,
      193734,
      293980,
      397844,
      402114,
      485904,
      248721,
      283244,
      372958,
      408073,
      327829,
      271028,
      187424,
      125768,
      164737,
      279457,
      234618,
      -88606,
      444754,
      1464078,
      841219,
      678792,
      6763,
      5715,
      5907,
      4434,
      4965,
      5457,
      6361,
      7364,
      8330,
      9235,
      9736,
      10201,
      10693,
      10726,
      11658,
      13779,
      14501,
      15486,
      16530,
      18066,
      18342,
      19582,
      20868,
      21936,
      22861,
      8708,
      8163,
      8346,
      4250,
      4533,
      5166,
      5510,
      5889,
      6396,
      6992,
      7172,
      7274,
      7563,
      8401,
      9104,
      8466,
      9282,
      9818,
      10221,
      10507,
      10320,
      10727,
      11645,
      12629,
      12925,
      317,
      340,
      371,
      430,
      450,
      460,
      473,
      520,
      577,
      647,
      676,
      688,
      664,
      1849,
      1966,
      2100,
      2186,
      2387,
      2538,
      2720,
      2707,
      2878,
      3041,
      3244,
      3383,
      716095,
      728075,
      732792,
      745237,
      843124,
      966166,
      1126193,
      1183166,
      1336674,
      1157207,
      1223241,
      1367184,
      1444530,
      1430436,
      1450234,
      1420752,
      1407888,
      1500759,
      1668631,
      1707679,
      1544376,
      2051152,
      3229855,
      2772274,
      2769269,
      208477,
      209395,
      224307,
      217829,
      271284,
      329766,
      382468,
      381068,
      449209,
      352230,
      397712,
      464558,
      478823,
      435505,
      390285,
      331838,
      308163,
      344468,
      419675,
      415563,
      307423,
      642569,
      1311860,
      892899,
      809171,
      192766,
      197237,
      198871,
      200785,
      215515,
      231707,
      256194,
      279098,
      276835,
      275943,
      296684,
      307877,
      320918,
      335144,
      348076,
      359281,
      375921,
      396160,
      414079,
      421870,
      428205,
      460225,
      487005,
      492477,
      511784,
      1273,
      1328,
      1243,
      1532,
      1660,
      1768,
      2063,
      2576,
      1973,
      2431,
      2377,
      1754,
      1887,
      2246,
      1880,
      295,
      206,
      91,
      73,
      44,
      64,
      48,
      32,
      46,
      30,
      133544,
      142603,
      152362,
      156634,
      164866,
      174435,
      189891,
      205979,
      225403,
      233882,
      244134,
      259933,
      278074,
      293642,
      313710,
      326170,
      331758,
      340982,
      358847,
      378773,
      382529,
      404059,
      430795,
      473708,
      492352,
      163707,
      159319,
      135472,
      143003,
      163622,
      199870,
      266194,
      284498,
      352124,
      259568,
      249358,
      299430,
      323828,
      322096,
      349943,
      360383,
      348783,
      373494,
      426535,
      437192,
      371939,
      488078,
      935950,
      845116,
      884289,
      45010,
      55471,
      56382,
      57688,
      60683,
      68065,
      96684,
      122926,
      127679,
      88954,
      81764,
      84655,
      75956,
      79877,
      92318,
      100426,
      96519,
      96650,
      95068,
      93713,
      88579,
      67477,
      95254,
      167185,
      240620,
      42591,
      52015,
      53583,
      53817,
      54787,
      56189,
      70967,
      89362,
      113490,
      88258,
      81414,
      83651,
      75737,
      79727,
      92159,
      100514,
      92548,
      93240,
      87942,
      87330,
      81189,
      62596,
      88959,
      155113,
      216677,
      2419,
      3456,
      2799,
      3871,
      5896,
      11876,
      25717,
      33564,
      14189,
      696,
      350,
      1004,
      219,
      150,
      159,
      -88,
      3971,
      3410,
      7126,
      6383,
      7389,
      4881,
      6295,
      12072,
      23943,
      8200,
      12694,
      18399,
      20410,
      23585,
      30368,
      41199,
      51220,
      69486,
      69912,
      65552,
      86926,
      97199,
      108375,
      133157,
      151925,
      156159,
      169866,
      199569,
      229040,
      202390,
      221124,
      294599,
      386949,
      389463,
      6498,
      6948,
      13354,
      15277,
      18363,
      22229,
      28606,
      37214,
      52546,
      54424,
      52733,
      73574,
      83287,
      93945,
      110511,
      136542,
      140415,
      153929,
      182800,
      208961,
      187337,
      210607,
      259246,
      308614,
      326857,
      1702,
      5746,
      5045,
      5133,
      5222,
      8139,
      12593,
      14006,
      16940,
      15489,
      12818,
      13352,
      13887,
      14421,
      22646,
      15382,
      15742,
      15937,
      16738,
      20057,
      15030,
      10494,
      35258,
      78309,
      62578,
      0,
      0,
      0,
      0,
      0,
      0,
      0,
      0,
      0,
      0,
      0,
      0,
      25,
      9,
      1,
      1,
      2,
      0,
      31,
      23,
      23,
      24,
      94,
      27,
      28,
      95562,
      76647,
      58753,
      63465,
      77888,
      100451,
      125736,
      108852,
      152610,
      98299,
      100263,
      125833,
      148431,
      131604,
      121472,
      94250,
      67002,
      86443,
      114802,
      97393,
      59100,
      181954,
      528638,
      276918,
      234086,
      95396,
      76456,
      58596,
      62538,
      76825,
      99562,
      124845,
      108817,
      152576,
      98285,
      100258,
      125820,
      148445,
      131604,
      121447,
      94145,
      67188,
      86620,
      114510,
      97376,
      59075,
      181937,
      528720,
      277003,
      234153,
      166,
      191,
      157,
      927,
      1063,
      889,
      891,
      35,
      34,
      14,
      6,
      12,
      -14,
      0,
      25,
      105,
      -186,
      -177,
      293,
      17,
      26,
      17,
      -82,
      -85,
      -66,
      10685,
      10685,
      0,
      0,
      0,
      0,
      0,
      0,
      0,
      0,
      0,
      0,
      0,
      0,
      0,
      10419,
      26589,
      17726,
      14333,
      14798,
      19706,
      15169,
      11108,
      8094,
      17604,
      4251,
      3822,
      1938,
      1440,
      1466,
      985,
      2576,
      1501,
      2348,
      2402,
      1779,
      2017,
      2243,
      2240,
      2996,
      3363,
      2515,
      2810,
      2763,
      2246,
      2163,
      2354,
      6352,
      5970,
      2516,
      4212,
      3777,
      1879,
      1380,
      1398,
      912,
      2499,
      1415,
      2257,
      2305,
      1673,
      1914,
      2134,
      2123,
      1980,
      2011,
      1864,
      1395,
      2242,
      1986,
      1942,
      2180,
      6170,
      5172,
      1786,
      3587,
      3467,
      1770,
      1229,
      1217,
      588,
      2350,
      764,
      1842,
      1470,
      1373,
      1517,
      1781,
      1700,
      1536,
      1551,
      1403,
      939,
      1780,
      1505,
      1418,
      940,
      1050,
      1319,
      1180,
      625,
      310,
      109,
      151,
      181,
      324,
      149,
      651,
      415,
      835,
      300,
      397,
      353,
      423,
      444,
      460,
      461,
      456,
      462,
      481,
      524,
      1240,
      5120,
      3852,
      606,
      39,
      45,
      59,
      60,
      68,
      73,
      77,
      86,
      91,
      98,
      106,
      103,
      108,
      117,
      1016,
      1352,
      651,
      1415,
      521,
      260,
      221,
      174,
      182,
      798,
      730,
      12864,
      15862,
      17615,
      18128,
      20804,
      22407,
      23012,
      25792,
      26217,
      26982,
      27346,
      28091,
      29874,
      30934,
      33005,
      35317,
      35933,
      38049,
      41121,
      44073,
      42837,
      43813,
      50287,
      53603,
      56519,
      3463,
      2331,
      2921,
      7326,
      5373,
      6214,
      6372,
      4155,
      4914,
      6172,
      5630,
      5539,
      11125,
      10869,
      13335,
      7468,
      7124,
      7514,
      8298,
      10164,
      11378,
      12360,
      13926,
      14425,
      15125,
      1078,
      882,
      502,
      643,
      1083,
      1283,
      1343,
      868,
      1886,
      2388,
      1600,
      1393,
      7080,
      7273,
      8225,
      2845,
      1977,
      2060,
      2184,
      2498,
      2438,
      2877,
      3102,
      3706,
      3845,
      0,
      0,
      0,
      0,
      0,
      0,
      0,
      0,
      0,
      0,
      0,
      0,
      0,
      0,
      0,
      0,
      0,
      0,
      0,
      0,
      0,
      0,
      0,
      0,
      0,
      1078,
      882,
      502,
      643,
      1083,
      1283,
      1343,
      868,
      1886,
      2388,
      1600,
      1393,
      7080,
      7273,
      8225,
      2845,
      1977,
      2060,
      2184,
      2498,
      2438,
      2877,
      3102,
      3706,
      3845,
      794,
      865,
      833,
      1144,
      1364,
      1412,
      1686,
      1823,
      1828,
      1732,
      2152,
      2015,
      1978,
      1951,
      2430,
      2182,
      2832,
      3247,
      3189,
      3802,
      3703,
      5661,
      5353,
      4962,
      4322,
      1592,
      583,
      1532,
      5539,
      2924,
      3227,
      3228,
      1459,
      1175,
      1914,
      1826,
      2125,
      2028,
      1598,
      2413,
      2028,
      1920,
      1839,
      2135,
      2287,
      2629,
      2694,
      4101,
      4108,
      5049,
      0,
      0,
      54,
      0,
      2,
      292,
      115,
      5,
      25,
      138,
      52,
      7,
      39,
      47,
      267,
      412,
      395,
      369,
      790,
      1576,
      1769,
      1128,
      1371,
      1648,
      1909,
      482346,
      510784,
      587276,
      605587,
      630405,
      661904,
      713870,
      755318,
      804324,
      863965,
      904712,
      959359,
      1006161,
      1056688,
      1125793,
      1194203,
      1238267,
      1285864,
      1327966,
      1387053,
      1571243,
      1579127,
      1676156,
      1832790,
      1985679,
      47383,
      49950,
      86041,
      92267,
      98168,
      102930,
      109863,
      117137,
      125833,
      133053,
      141464,
      148953,
      157582,
      166631,
      176811,
      185465,
      190032,
      198083,
      206801,
      215062,
      223085,
      236188,
      250849,
      268869,
      285379,
      35840,
      42693,
      54605,
      52874,
      55132,
      58012,
      61127,
      64025,
      68515,
      75373,
      77445,
      79015,
      82107,
      87451,
      94420,
      101325,
      106174,
      111795,
      116209,
      123627,
      133477,
      141582,
      158043,
      170678,
      181998,
      24223,
      24022,
      27688,
      28396,
      30411,
      31214,
      33819,
      37081,
      40141,
      44247,
      42919,
      46509,
      50037,
      50699,
      54212,
      58902,
      61961,
      64493,
      68878,
      74350,
      80768,
      86907,
      96345,
      107009,
      114949,
      19513,
      23621,
      22362,
      26423,
      24668,
      28886,
      47892,
      52059,
      42855,
      26614,
      22518,
      20517,
      15135,
      14438,
      13907,
      14012,
      11927,
      10561,
      12134,
      12041,
      11481,
      8445,
      15167,
      29036,
      45973,
      19442,
      23536,
      22255,
      26312,
      24554,
      28765,
      47767,
      51924,
      42704,
      26450,
      22338,
      20323,
      14940,
      14240,
      13595,
      13658,
      11542,
      10176,
      11751,
      11655,
      11066,
      8033,
      14748,
      28573,
      45494,
      16526,
      19471,
      18882,
      20936,
      18144,
      17181,
      26282,
      19657,
      22705,
      23933,
      21973,
      19715,
      14814,
      14205,
      13559,
      13708,
      11565,
      9831,
      11751,
      11655,
      11066,
      8033,
      14748,
      28573,
      45494,
      2916,
      4065,
      3373,
      5376,
      6410,
      11584,
      21485,
      32267,
      19999,
      2517,
      365,
      608,
      126,
      35,
      36,
      -50,
      -23,
      345,
      0,
      0,
      0,
      0,
      0,
      0,
      0,
      71,
      85,
      108,
      111,
      113,
      120,
      125,
      135,
      151,
      164,
      180,
      193,
      195,
      197,
      312,
      355,
      386,
      385,
      383,
      386,
      415,
      413,
      419,
      463,
      479,
      17873,
      19472,
      24874,
      26919,
      28560,
      29737,
      30344,
      30871,
      32920,
      34116,
      36965,
      37389,
      38751,
      40048,
      42747,
      45513,
      47834,
      48428,
      48919,
      49914,
      50486,
      55484,
      60181,
      65571,
      70128,
      188616,
      202004,
      218414,
      239434,
      246794,
      251648,
      259519,
      270408,
      289926,
      317013,
      335112,
      356724,
      376221,
      392949,
      416535,
      444297,
      460728,
      473440,
      485542,
      504830,
      560367,
      575277,
      594272,
      646189,
      700591,
      28203,
      29005,
      29583,
      31430,
      31090,
      31827,
      31481,
      31222,
      34355,
      37963,
      38532,
      38425,
      40074,
      41832,
      44363,
      47206,
      49873,
      51384,
      53195,
      55418,
      78197,
      73266,
      104927,
      88606,
      90004,
      111178,
      116771,
      120618,
      104702,
      113459,
      124611,
      136550,
      150098,
      165199,
      191399,
      205799,
      226816,
      241572,
      259032,
      277689,
      293510,
      304921,
      322833,
      330100,
      344880,
      381569,
      392363,
      382583,
      443411,
      476186,
      91996,
      95457,
      95034,
      77922,
      82820,
      89070,
      98825,
      108597,
      119577,
      138974,
      150534,
      171342,
      185498,
      196348,
      210179,
      219336,
      229143,
      244799,
      250451,
      257729,
      281082,
      287286,
      280411,
      317323,
      348034,
      0,
      0,
      0,
      0,
      0,
      0,
      0,
      0,
      0,
      0,
      0,
      0,
      0,
      0,
      0,
      0,
      0,
      0,
      0,
      0,
      0,
      0,
      0,
      0,
      0,
      91996,
      95457,
      95034,
      77922,
      82820,
      89070,
      98825,
      108597,
      119577,
      138974,
      150534,
      171342,
      185498,
      196348,
      210179,
      219336,
      229143,
      244799,
      250451,
      257729,
      281082,
      287286,
      280411,
      317323,
      348034,
      5802,
      6070,
      9023,
      9407,
      12627,
      14921,
      15586,
      15044,
      16177,
      19192,
      19104,
      20016,
      20886,
      22642,
      29138,
      32444,
      33278,
      37272,
      39124,
      41566,
      47950,
      50305,
      49295,
      53667,
      54701,
      3822,
      4213,
      3998,
      4013,
      4450,
      4424,
      4446,
      4714,
      5381,
      5554,
      5890,
      6246,
      6592,
      6898,
      5930,
      5983,
      6354,
      6315,
      6584,
      6779,
      9182,
      9712,
      2277,
      2753,
      2265,
      9559,
      11030,
      12564,
      13358,
      13562,
      16196,
      17694,
      21742,
      24064,
      27678,
      30271,
      29212,
      28596,
      33144,
      32442,
      35747,
      36146,
      34446,
      33941,
      38806,
      43355,
      45061,
      50599,
      69668,
      71186,
      9517,
      3247,
      3090,
      3141,
      2123,
      3039,
      3274,
      2415,
      4581,
      4187,
      3957,
      5012,
      4683,
      3608,
      5109,
      3972,
      4817,
      4846,
      6187,
      6931,
      51813,
      9614,
      13790,
      13419,
      20472,
      8755,
      2218,
      2343,
      2414,
      1324,
      1161,
      2356,
      1445,
      3443,
      3067,
      2689,
      3513,
      3404,
      2231,
      3987,
      3102,
      3994,
      4083,
      5351,
      5916,
      50746,
      8423,
      9293,
      8995,
      8334,
      0,
      0,
      0,
      0,
      0,
      0,
      0,
      622,
      796,
      1274,
      1639,
      2001,
      2359,
      1629,
      1287,
      1795,
      2627,
      2512,
      2670,
      3128,
      42259,
      6388,
      7385,
      6783,
      6964,
      0,
      0,
      0,
      0,
      0,
      0,
      0,
      823,
      2647,
      1794,
      1050,
      1512,
      1045,
      602,
      2699,
      1306,
      1367,
      1571,
      2681,
      2788,
      8487,
      2035,
      1907,
      2212,
      1370,
      762,
      1029,
      747,
      727,
      799,
      1878,
      919,
      970,
      1138,
      1120,
      1268,
      1500,
      1280,
      1377,
      1122,
      870,
      823,
      763,
      836,
      1016,
      1067,
      1191,
      4497,
      4424,
      12138,
      233749,
      217291,
      145516,
      139650,
      212718,
      304262,
      412324,
      427848,
      532350,
      293242,
      318529,
      407825,
      438368,
      373747,
      324440,
      226549,
      169621,
      214895,
      340665,
      320626,
      -26866,
      472025,
      1553699,
      939484,
      783589,
      1583,
      145,
      5165,
      6655,
      8512,
      9944,
      13100,
      15291,
      19401,
      20394,
      13634,
      15405,
      13565,
      21999,
      29431,
      29122,
      30845,
      38052,
      41221,
      50671,
      39088,
      44454,
      41481,
      54620,
      54085,
      26330,
      24887,
      32463,
      36333,
      40929,
      43180,
      48704,
      53555,
      60312,
      65282,
      57460,
      62771,
      64306,
      75766,
      85388,
      89058,
      94854,
      104051,
      116072,
      127194,
      130562,
      135175,
      145540,
      165168,
      177841,
      26398,
      25115,
      32688,
      36499,
      41062,
      43409,
      49001,
      54454,
      61529,
      66063,
      58267,
      63186,
      64825,
      76231,
      86077,
      90096,
      95487,
      105667,
      117410,
      128365,
      131384,
      136375,
      148346,
      168717,
      182319,
      20244,
      18575,
      24682,
      27725,
      31400,
      32865,
      36998,
      41012,
      46530,
      49678,
      41025,
      45176,
      46043,
      55388,
      63670,
      65983,
      69896,
      78308,
      88266,
      97188,
      100559,
      103512,
      113739,
      131788,
      143675,
      6154,
      6541,
      8007,
      8775,
      9662,
      10544,
      12003,
      13442,
      14999,
      16385,
      17242,
      18010,
      18782,
      20844,
      22406,
      24114,
      25590,
      27359,
      29144,
      31177,
      30825,
      32863,
      34608,
      36929,
      38644,
      -68,
      -229,
      -226,
      -166,
      -133,
      -229,
      -297,
      -899,
      -1218,
      -781,
      -807,
      -415,
      -519,
      -465,
      -689,
      -1038,
      -633,
      -1616,
      -1338,
      -1171,
      -822,
      -1200,
      -2806,
      -3549,
      -4478,
      -24497,
      -24316,
      -28059,
      -28826,
      -30861,
      -31674,
      -34292,
      -37601,
      -40718,
      -44894,
      -43595,
      -47197,
      -50701,
      -52548,
      -56178,
      -61002,
      -64147,
      -66880,
      -71416,
      -77070,
      -83475,
      -89785,
      -99386,
      -110253,
      -118332,
      -17737,
      -18277,
      -20635,
      -21152,
      -21942,
      -22935,
      -24388,
      -26423,
      -28517,
      -31667,
      -29063,
      -31117,
      -33456,
      -34423,
      -37060,
      -40747,
      -42622,
      -44231,
      -47126,
      -50854,
      -56158,
      -60873,
      -68113,
      -76511,
      -82743,
      -6486,
      -5745,
      -7053,
      -7244,
      -8469,
      -8279,
      -9431,
      -10658,
      -11624,
      -12580,
      -13856,
      -15392,
      -16581,
      -16276,
      -17152,
      -18155,
      -19340,
      -20262,
      -21752,
      -23496,
      -24610,
      -26034,
      -28232,
      -30498,
      -32205,
      -274,
      -294,
      -371,
      -430,
      -450,
      -460,
      -473,
      -520,
      -577,
      -647,
      -676,
      -688,
      -664,
      -1849,
      -1966,
      -2100,
      -2186,
      -2387,
      -2538,
      -2720,
      -2707,
      -2878,
      -3041,
      -3244,
      -3383,
      -250,
      -426,
      761,
      -853,
      -1557,
      -1562,
      -1312,
      -663,
      -193,
      6,
      -231,
      -169,
      -40,
      -1219,
      221,
      1066,
      138,
      881,
      -3435,
      546,
      -8000,
      -937,
      -4673,
      -295,
      -5424,
      140,
      132,
      1235,
      96,
      50,
      136,
      122,
      410,
      454,
      636,
      810,
      640,
      774,
      1336,
      595,
      1254,
      626,
      1173,
      749,
      728,
      692,
      736,
      504,
      1821,
      839,
      -390,
      -558,
      -474,
      -949,
      -1607,
      -1699,
      -1434,
      -1073,
      -646,
      -630,
      -1041,
      -809,
      -814,
      -2555,
      -374,
      -189,
      -488,
      -292,
      -4184,
      -182,
      -8692,
      -1672,
      -5177,
      -2116,
      -6263,
      483929,
      510929,
      592441,
      612241,
      638917,
      671848,
      726970,
      770609,
      823725,
      884359,
      918346,
      974763,
      1019726,
      1078687,
      1155225,
      1223325,
      1269112,
      1323916,
      1369187,
      1437723,
      1610330,
      1623580,
      1717638,
      1887410,
      2039764,
      232166,
      217146,
      140351,
      132995,
      204207,
      294318,
      399224,
      412557,
      512949,
      272848,
      304895,
      392420,
      424803,
      351748,
      295009,
      197427,
      138775,
      176842,
      299444,
      269956,
      -65954,
      427571,
      1512218,
      884864,
      729505,
      4800,
      5058,
      5828,
      4335,
      4838,
      5337,
      6222,
      7243,
      8189,
      9078,
      9588,
      10024,
      10480,
      10602,
      11528,
      13629,
      14298,
      15260,
      16275,
      17776,
      17758,
      19112,
      19944,
      21260,
      22250,
      6298,
      6737,
      7491,
      3432,
      3779,
      4125,
      4641,
      4983,
      5345,
      5691,
      6001,
      6230,
      6525,
      7256,
      7712,
      7105,
      7812,
      8412,
      8965,
      9281,
      8928,
      9382,
      10034,
      10697,
      11179,
      274,
      294,
      371,
      430,
      450,
      460,
      473,
      520,
      577,
      647,
      676,
      688,
      664,
      1849,
      1966,
      2100,
      2186,
      2387,
      2538,
      2720,
      2707,
      2878,
      3041,
      3244,
      3383,
      227713,
      251619,
      225785,
      224107,
      234677,
      252579,
      272442,
      295601,
      313214,
      345247,
      370835,
      394239,
      420957,
      443904,
      469127,
      497701,
      519624,
      546568,
      569281,
      592933,
      613602,
      686435,
      669173,
      737130,
      786016,
      90623,
      103204,
      80918,
      94111,
      97853,
      106471,
      112979,
      116630,
      119826,
      130884,
      138980,
      133008,
      143775,
      151915,
      158035,
      171217,
      180852,
      187692,
      197697,
      203444,
      207539,
      266365,
      237590,
      248821,
      259600,
      4219,
      4327,
      4432,
      4761,
      5057,
      5874,
      6441,
      7070,
      7750,
      8051,
      8681,
      9130,
      9617,
      10484,
      11233,
      12751,
      13886,
      15254,
      15881,
      16391,
      16477,
      17238,
      17763,
      19278,
      19155,
      0,
      0,
      0,
      0,
      0,
      0,
      0,
      0,
      0,
      0,
      0,
      0,
      0,
      0,
      0,
      0,
      0,
      0,
      0,
      0,
      0,
      0,
      0,
      0,
      0,
      1102,
      1882,
      1351,
      1416,
      1465,
      1526,
      1634,
      1774,
      1950,
      2094,
      2211,
      2356,
      2498,
      2636,
      2740,
      2883,
      3021,
      3675,
      3813,
      4087,
      4232,
      4633,
      5296,
      5298,
      5563,
      9560,
      13454,
      11337,
      11829,
      11235,
      11755,
      13697,
      18160,
      16098,
      13959,
      12919,
      17540,
      15408,
      14856,
      17114,
      16697,
      15061,
      14893,
      17303,
      21597,
      15208,
      17449,
      24260,
      34494,
      33983,
      5164,
      6251,
      7216,
      6451,
      4468,
      4941,
      5674,
      6698,
      7585,
      5069,
      4456,
      5310,
      5770,
      5726,
      5992,
      5570,
      4933,
      4563,
      4936,
      5943,
      4099,
      3620,
      6743,
      12190,
      13921,
      5164,
      6251,
      7216,
      6451,
      4468,
      4941,
      5674,
      6698,
      7585,
      5069,
      4456,
      5310,
      5770,
      5726,
      5992,
      5570,
      4933,
      4563,
      4936,
      5943,
      4099,
      3620,
      6743,
      12190,
      13921,
      0,
      0,
      0,
      0,
      0,
      0,
      0,
      0,
      0,
      0,
      0,
      0,
      0,
      0,
      0,
      0,
      0,
      0,
      0,
      0,
      0,
      0,
      0,
      0,
      0,
      2894,
      3702,
      2376,
      2825,
      2637,
      3396,
      4659,
      6545,
      5313,
      5460,
      5222,
      8736,
      5488,
      5523,
      7401,
      7947,
      7561,
      7385,
      9103,
      11890,
      7991,
      9480,
      11869,
      15432,
      13850,
      2894,
      3702,
      2376,
      2825,
      2637,
      3396,
      4659,
      6545,
      5313,
      5460,
      5222,
      8736,
      4948,
      5066,
      6939,
      7580,
      7222,
      7046,
      8755,
      11481,
      7641,
      9015,
      11390,
      14962,
      13375,
      0,
      0,
      0,
      0,
      0,
      0,
      0,
      0,
      0,
      0,
      0,
      0,
      0,
      0,
      0,
      0,
      0,
      0,
      0,
      0,
      0,
      0,
      0,
      0,
      0,
      0,
      0,
      0,
      0,
      0,
      0,
      0,
      0,
      0,
      0,
      0,
      0,
      540,
      457,
      462,
      367,
      339,
      339,
      348,
      409,
      350,
      465,
      479,
      470,
      475,
      721,
      2766,
      971,
      1841,
      3352,
      2466,
      2534,
      3039,
      1382,
      1588,
      1477,
      1576,
      2333,
      1809,
      2039,
      1793,
      905,
      1053,
      1060,
      1166,
      898,
      1395,
      1124,
      2169,
      2253,
      0,
      0,
      0,
      0,
      0,
      0,
      0,
      0,
      0,
      0,
      0,
      0,
      0,
      0,
      0,
      0,
      0,
      0,
      0,
      0,
      0,
      0,
      0,
      0,
      0,
      721,
      2766,
      971,
      1841,
      3352,
      2466,
      2534,
      3039,
      1382,
      1588,
      1477,
      1576,
      2333,
      1809,
      2039,
      1793,
      905,
      1053,
      1060,
      1166,
      898,
      1395,
      1124,
      2169,
      2253,
      0,
      0,
      0,
      0,
      0,
      0,
      0,
      0,
      0,
      0,
      0,
      0,
      0,
      0,
      0,
      0,
      0,
      0,
      0,
      0,
      0,
      0,
      0,
      0,
      0,
      781,
      735,
      774,
      712,
      778,
      952,
      831,
      1878,
      1818,
      1842,
      1764,
      1919,
      1816,
      1798,
      1683,
      1387,
      1662,
      1892,
      2204,
      2598,
      2220,
      2954,
      4524,
      4703,
      3959,
      615,
      552,
      591,
      516,
      569,
      730,
      596,
      683,
      698,
      551,
      583,
      540,
      570,
      567,
      538,
      407,
      682,
      626,
      671,
      704,
      755,
      725,
      744,
      780,
      855,
      0,
      0,
      0,
      0,
      0,
      0,
      0,
      0,
      0,
      0,
      0,
      0,
      0,
      0,
      0,
      0,
      0,
      0,
      0,
      0,
      0,
      0,
      0,
      0,
      0,
      615,
      552,
      591,
      516,
      569,
      730,
      596,
      683,
      698,
      551,
      583,
      540,
      570,
      567,
      538,
      407,
      682,
      626,
      671,
      704,
      755,
      725,
      744,
      780,
      855,
      166,
      183,
      183,
      196,
      209,
      222,
      235,
      1195,
      1121,
      1290,
      1182,
      1380,
      1245,
      1231,
      1145,
      980,
      980,
      1266,
      1532,
      1893,
      1466,
      2228,
      3780,
      3923,
      3104,
      27629,
      30576,
      29940,
      31490,
      33417,
      34678,
      35596,
      40702,
      45019,
      47977,
      53838,
      57424,
      60736,
      63537,
      66031,
      70154,
      71780,
      75071,
      78048,
      82895,
      80846,
      84815,
      94774,
      100986,
      108033,
      94580,
      98176,
      97807,
      80500,
      85650,
      92274,
      102096,
      111265,
      122570,
      142282,
      154207,
      174780,
      188923,
      200476,
      213974,
      223999,
      235023,
      249984,
      256539,
      264520,
      289300,
      295934,
      289489,
      328252,
      359682,
      91995,
      95457,
      95034,
      77922,
      82820,
      89070,
      98825,
      108597,
      119577,
      138974,
      150534,
      171342,
      185498,
      196348,
      210179,
      219336,
      229143,
      244799,
      250451,
      257729,
      281082,
      287286,
      280411,
      317323,
      348034,
      91995,
      95457,
      95034,
      77922,
      82820,
      89070,
      98825,
      108597,
      119577,
      138974,
      150534,
      171342,
      185498,
      196348,
      210179,
      219336,
      229143,
      244799,
      250451,
      257729,
      281082,
      287286,
      280411,
      317323,
      348034,
      0,
      0,
      0,
      0,
      0,
      0,
      0,
      0,
      0,
      0,
      0,
      0,
      0,
      0,
      0,
      0,
      0,
      0,
      0,
      0,
      0,
      0,
      0,
      0,
      0,
      0,
      0,
      0,
      0,
      0,
      0,
      0,
      0,
      32,
      37,
      55,
      49,
      56,
      66,
      70,
      73,
      109,
      110,
      101,
      110,
      52,
      87,
      140,
      94,
      94,
      2585,
      2719,
      2773,
      2577,
      2830,
      3204,
      3271,
      2669,
      2961,
      3271,
      3617,
      3390,
      3369,
      4062,
      3724,
      4590,
      5771,
      5074,
      5988,
      6681,
      6199,
      8561,
      8938,
      10835,
      11554,
      0,
      0,
      0,
      0,
      0,
      0,
      0,
      0,
      0,
      0,
      0,
      0,
      0,
      0,
      0,
      0,
      0,
      0,
      0,
      0,
      0,
      0,
      0,
      0,
      0,
      224608,
      253196,
      216605,
      228649,
      235408,
      246017,
      264679,
      292477,
      324565,
      349313,
      375149,
      398345,
      426104,
      451250,
      475384,
      491349,
      509811,
      536570,
      562459,
      594347,
      605935,
      643087,
      687672,
      754133,
      804262,
      129663,
      144118,
      120067,
      127035,
      130916,
      136841,
      144638,
      157409,
      173756,
      187422,
      197070,
      210598,
      223798,
      237736,
      248955,
      258288,
      269887,
      282455,
      296427,
      312090,
      315291,
      329978,
      347918,
      370487,
      397552,
      42972,
      49409,
      46029,
      49349,
      51051,
      53097,
      58115,
      64424,
      71953,
      78671,
      84014,
      87912,
      90490,
      96125,
      101079,
      107654,
      110533,
      118170,
      123726,
      130901,
      134829,
      150061,
      162723,
      176309,
      179843,
      16406,
      17385,
      14833,
      15107,
      16294,
      17597,
      19098,
      21088,
      23548,
      24758,
      31029,
      33242,
      36955,
      37543,
      40371,
      43282,
      45118,
      47650,
      50439,
      52778,
      55875,
      59581,
      65342,
      69751,
      73197,
      6688,
      9414,
      9699,
      8597,
      7039,
      6932,
      7690,
      11341,
      12092,
      10634,
      10668,
      12416,
      12984,
      12999,
      13365,
      12852,
      12381,
      12083,
      12189,
      14027,
      12456,
      10370,
      15434,
      27366,
      34923,
      6559,
      9271,
      9546,
      8435,
      6871,
      6757,
      7505,
      11144,
      11882,
      10404,
      10421,
      12148,
      12699,
      12693,
      13033,
      12486,
      11974,
      11645,
      11739,
      13559,
      11989,
      9882,
      14903,
      26760,
      34257,
      6559,
      9271,
      9546,
      8435,
      6871,
      6757,
      7505,
      11144,
      11882,
      10404,
      10421,
      12148,
      12699,
      12693,
      13033,
      12486,
      11974,
      11645,
      11739,
      13559,
      11989,
      9882,
      14903,
      26760,
      34257,
      0,
      0,
      0,
      0,
      0,
      0,
      0,
      0,
      0,
      0,
      0,
      0,
      0,
      0,
      0,
      0,
      0,
      0,
      0,
      0,
      0,
      0,
      0,
      0,
      0,
      129,
      143,
      153,
      162,
      168,
      175,
      185,
      197,
      210,
      230,
      247,
      268,
      285,
      306,
      332,
      366,
      407,
      437,
      450,
      468,
      467,
      488,
      531,
      606,
      666,
      5455,
      7919,
      5253,
      6266,
      8335,
      9774,
      11985,
      12089,
      13926,
      15992,
      17441,
      18769,
      19996,
      21143,
      22918,
      23555,
      24618,
      25582,
      27112,
      28321,
      27861,
      30728,
      31430,
      34458,
      36681,
      8555,
      9436,
      8935,
      9328,
      9649,
      9112,
      9493,
      10257,
      11044,
      12312,
      13147,
      13288,
      13637,
      14575,
      15410,
      16336,
      17740,
      19934,
      19717,
      19414,
      18962,
      19269,
      21091,
      27196,
      29745,
      3412,
      5173,
      3278,
      3704,
      3952,
      4267,
      5000,
      4944,
      5288,
      5272,
      6958,
      7010,
      7052,
      7558,
      7197,
      7873,
      7965,
      8126,
      8997,
      9981,
      13191,
      14605,
      12886,
      13419,
      14274,
      9988,
      9234,
      7658,
      8218,
      6995,
      7651,
      8178,
      9811,
      11511,
      13073,
      12866,
      13187,
      19634,
      20922,
      23388,
      18892,
      19704,
      20972,
      22297,
      24416,
      25151,
      26293,
      28697,
      31771,
      34229,
      1077,
      881,
      502,
      643,
      1083,
      1283,
      1343,
      868,
      1886,
      2388,
      1600,
      1393,
      7080,
      7273,
      8225,
      2845,
      1977,
      2060,
      2184,
      2498,
      2438,
      2877,
      3102,
      3706,
      3845,
      1077,
      881,
      502,
      643,
      1083,
      1283,
      1343,
      868,
      1886,
      2388,
      1600,
      1393,
      7080,
      7273,
      8225,
      2845,
      1977,
      2060,
      2184,
      2498,
      2438,
      2877,
      3102,
      3706,
      3845,
      0,
      0,
      0,
      0,
      0,
      0,
      0,
      0,
      0,
      0,
      0,
      0,
      0,
      0,
      0,
      0,
      0,
      0,
      0,
      0,
      0,
      0,
      0,
      0,
      0,
      8907,
      8344,
      7152,
      7570,
      5907,
      6364,
      6832,
      8886,
      9555,
      10620,
      11201,
      11721,
      12491,
      13570,
      14934,
      15822,
      17493,
      18666,
      19872,
      21650,
      22472,
      23145,
      25283,
      27422,
      29848,
      4,
      9,
      4,
      4,
      4,
      4,
      4,
      57,
      70,
      65,
      65,
      74,
      63,
      78,
      228,
      226,
      235,
      246,
      240,
      268,
      242,
      271,
      313,
      642,
      536,
      0,
      0,
      0,
      0,
      0,
      0,
      0,
      0,
      0,
      0,
      0,
      0,
      0,
      0,
      0,
      0,
      0,
      0,
      0,
      0,
      0,
      0,
      0,
      0,
      0,
      1469,
      1108,
      853,
      1046,
      1177,
      745,
      482,
      1116,
      1448,
      1179,
      1956,
      1923,
      1558,
      2649,
      2700,
      2617,
      1865,
      1600,
      1555,
      2419,
      2317,
      2203,
      2151,
      3376,
      3818,
      1469,
      1108,
      853,
      1046,
      1177,
      745,
      482,
      1116,
      1448,
      1179,
      1956,
      1923,
      1558,
      2649,
      2700,
      2617,
      1865,
      1600,
      1555,
      2419,
      2317,
      2203,
      2151,
      3376,
      3818,
      0,
      0,
      0,
      0,
      0,
      0,
      0,
      0,
      0,
      150,
      825,
      654,
      405,
      1381,
      1452,
      1053,
      967,
      664,
      893,
      1010,
      1200,
      1112,
      1259,
      2358,
      2500,
      0,
      0,
      0,
      0,
      0,
      0,
      0,
      1116,
      1448,
      1029,
      1131,
      1269,
      1153,
      1268,
      1248,
      1564,
      898,
      936,
      662,
      1409,
      1117,
      1091,
      892,
      1018,
      1318,
      0,
      0,
      0,
      0,
      0,
      0,
      0,
      0,
      0,
      0,
      0,
      0,
      0,
      0,
      0,
      0,
      0,
      0,
      0,
      0,
      0,
      0,
      0,
      0,
      0,
      3105,
      -1577,
      9180,
      -4542,
      -732,
      6562,
      7763,
      3124,
      -11351,
      -4066,
      -4314,
      -4106,
      -5147,
      -7346,
      -6257,
      6352,
      9813,
      9998,
      6823,
      -1414,
      7667,
      43348,
      -18499,
      -17003,
      -18246,
      8200,
      9183,
      8331,
      11449,
      9741,
      6899,
      9143,
      13567,
      15694,
      20061,
      17337,
      15356,
      11583,
      16573,
      17724,
      16354,
      22820,
      22103,
      26810,
      33924,
      30318,
      26166,
      29641,
      26642,
      32467,
      25106,
      27983,
      24534,
      27338,
      27555,
      26230,
      29889,
      36421,
      40585,
      45639,
      49992,
      50324,
      50771,
      56035,
      59272,
      62932,
      70315,
      69791,
      77862,
      86974,
      86841,
      85280,
      94483,
      97393,
      105664,
      25409,
      28138,
      25086,
      27577,
      27971,
      26686,
      30176,
      36600,
      40747,
      46234,
      50043,
      50401,
      50841,
      56164,
      59366,
      64987,
      70458,
      73239,
      80559,
      90530,
      90091,
      89603,
      98024,
      100811,
      108687,
      24533,
      27197,
      25086,
      27577,
      27971,
      26686,
      30176,
      36600,
      40747,
      46234,
      50043,
      50401,
      50841,
      56164,
      59366,
      64987,
      70458,
      73239,
      80559,
      90530,
      90091,
      89603,
      98024,
      100811,
      108687,
      876,
      941,
      0,
      0,
      0,
      0,
      0,
      0,
      0,
      0,
      0,
      0,
      0,
      0,
      0,
      0,
      0,
      0,
      0,
      0,
      0,
      0,
      0,
      0,
      0,
      -303,
      -155,
      -552,
      -239,
      -417,
      -457,
      -287,
      -178,
      -162,
      -595,
      -51,
      -78,
      -71,
      -128,
      -93,
      -2055,
      -143,
      -3448,
      -2697,
      -3555,
      -3250,
      -4323,
      -3541,
      -3418,
      -3023,
      -16449,
      -17431,
      -14833,
      -15107,
      -16294,
      -17597,
      -19098,
      -21088,
      -23548,
      -24758,
      -31029,
      -33242,
      -36955,
      -37543,
      -40371,
      -43282,
      -45118,
      -47650,
      -50439,
      -52778,
      -55875,
      -59581,
      -65342,
      -69751,
      -73197,
      -15655,
      -16605,
      -14833,
      -15107,
      -16294,
      -17597,
      -19098,
      -21088,
      -23548,
      -24758,
      -31029,
      -33242,
      -36955,
      -37543,
      -40371,
      -43282,
      -45118,
      -47650,
      -50439,
      -52778,
      -55875,
      -59581,
      -65342,
      -69751,
      -73197,
      -751,
      -780,
      0,
      0,
      0,
      0,
      0,
      0,
      0,
      0,
      0,
      0,
      0,
      0,
      0,
      0,
      0,
      0,
      0,
      0,
      0,
      0,
      0,
      0,
      0,
      -43,
      -46,
      0,
      0,
      0,
      0,
      0,
      0,
      0,
      0,
      0,
      0,
      0,
      0,
      0,
      0,
      0,
      0,
      0,
      0,
      0,
      0,
      0,
      0,
      0,
      -457,
      -1369,
      -1370,
      -783,
      -1519,
      -1733,
      -1648,
      -1767,
      -1343,
      -820,
      -1626,
      -1726,
      -2232,
      -1920,
      -1178,
      -3296,
      -2377,
      -38,
      -613,
      -272,
      -648,
      467,
      500,
      -1000,
      0,
      594,
      1118,
      797,
      1030,
      391,
      675,
      927,
      1215,
      1078,
      1346,
      1156,
      1393,
      1356,
      1588,
      1793,
      1755,
      1074,
      974,
      458,
      662,
      489,
      1459,
      1500,
      1000,
      1000,
      -1051,
      -2487,
      -2167,
      -1813,
      -1910,
      -2408,
      -2575,
      -2982,
      -2421,
      -2166,
      -2782,
      -3119,
      -3588,
      -3507,
      -2971,
      -5051,
      -3451,
      -1012,
      -1071,
      -934,
      -1137,
      -992,
      -1000,
      -2000,
      -1000,
      232808,
      262379,
      224936,
      240098,
      245150,
      252916,
      273822,
      306044,
      340259,
      369374,
      392486,
      413701,
      437687,
      467823,
      493108,
      507704,
      532631,
      558673,
      589268,
      628271,
      636253,
      669253,
      717313,
      780776,
      836729,
      -5095,
      -10760,
      848,
      -15991,
      -10473,
      -338,
      -1379,
      -10443,
      -27045,
      -24127,
      -21651,
      -19462,
      -16730,
      -23919,
      -23981,
      -10003,
      -13007,
      -12105,
      -19987,
      -35338,
      -22652,
      17182,
      -48139,
      -43645,
      -50713,
      1963,
      657,
      79,
      99,
      127,
      120,
      139,
      121,
      142,
      157,
      149,
      177,
      213,
      125,
      130,
      151,
      203,
      227,
      254,
      290,
      584,
      471,
      924,
      676,
      611,
      2410,
      1426,
      855,
      818,
      754,
      1041,
      869,
      906,
      1051,
      1301,
      1171,
      1044,
      1038,
      1145,
      1392,
      1361,
      1470,
      1406,
      1256,
      1227,
      1392,
      1345,
      1611,
      1932,
      1747,
      43,
      46,
      0,
      0,
      0,
      0,
      0,
      0,
      0,
      0,
      0,
      0,
      0,
      0,
      0,
      0,
      0,
      0,
      0,
      0,
      0,
      0,
      0,
      0,
      0
    ]
  },
  "_metadata": {
    "source": "SSB",
    "title": "Government Revenue",
    "fetched_at": "2025-08-14T00:59:05.729650",
    "url": "https://data.ssb.no/api/v0/dataset/928194.json?lang=en"
  }
}